fyerstest/__init__.py
fyerstest/fyersApi.py
fyerstest/hsmFyers.py
fyerstest/ws.py
fyerspysdk1-1.7.dist-info/LICENSE.txt
fyerspysdk1-1.7.dist-info/METADATA
fyerspysdk1-1.7.dist-info/WHEEL
fyerspysdk1-1.7.dist-info/top_level.txt
fyerspysdk1-1.7.dist-info/RECORD
