Metadata-Version: 2.1
Name: fyerspysdk1
Version: 1.7
Summary: XX trc APIs.
Home-page: https://github.com
Author: my-Tech
Author-email: support@f.in
License: UNKNOWN
Platform: UNKNOWN
Classifier: Programming Language :: Python :: 3
Classifier: License :: OSI Approved :: MIT License
Classifier: Operating System :: OS Independent
License-File: LICENSE.txt
Requires-Dist: requests (==2.25.1)
Requires-Dist: tornado (==6.1)
Requires-Dist: asyncio (==3.4.3)
Requires-Dist: websockets (==8.1)
Requires-Dist: websocket-client (==1.2.1)
Requires-Dist: aiohttp (==3.8.4)
